ccomplex
